mkdocs_json_schema_plugin/__init__.py
mkdocs_json_schema_plugin/jsonschema.py
mkdocs_json_schema_plugin/jsonschema_tests.py
MkDocsJsonSchemaPlugin-0.0.2.dist-info/LICENSE
MkDocsJsonSchemaPlugin-0.0.2.dist-info/METADATA
MkDocsJsonSchemaPlugin-0.0.2.dist-info/WHEEL
MkDocsJsonSchemaPlugin-0.0.2.dist-info/entry_points.txt
MkDocsJsonSchemaPlugin-0.0.2.dist-info/top_level.txt
MkDocsJsonSchemaPlugin-0.0.2.dist-info/RECORD
