Metadata-Version: 2.1
Name: MkDocsJsonSchemaPlugin
Version: 0.0.2
Summary: MkDocs Plugin to parse json schemas.
Home-page: https://github.com/galamdring/mkdocs-json-schema-plugin
Author: Luke McKechnie
Author-email: galamdring@gmail.com
License: MIT license
Keywords: mkdocs,plugin,json,schema
Platform: UNKNOWN
Classifier: Development Status :: 4 - Beta
Classifier: License :: OSI Approved :: MIT License
Classifier: Programming Language :: Python :: 3
Classifier: Programming Language :: Python :: 3.4
Classifier: Programming Language :: Python :: 3.5
Classifier: Programming Language :: Python :: 3.6
Classifier: Programming Language :: Python :: 3.7
Requires-Python: >=3.4, <4
Requires-Dist: mkdocs
Requires-Dist: webpreview (>=1.6.0)
